Metadata-Version: 1.1
Name: meeting
Version: 0.0.1a0
Summary: Festival management application: Tickets E-Commerce, Tickets validation on Lobby (Web, Paper, Guest, Local Purchase) and Sells on Wristband/Card (Beverage, Food, Souvenir, etc).
Home-page: http://github.com/mauler/meeting
Author: Paulo R
Author-email: proberto.macedo@gmail.com
License: UNKNOWN
Keywords: festival rfid qrcode barcode tickets
Platform: UNKNOWN
Classifier: Environment :: Web Environment
Classifier: Framework :: Django
Classifier: Intended Audience :: Developers
Classifier: Operating System :: OS Independent
Classifier: Programming Language :: Python
Classifier: Programming Language :: Python :: 3 :: Only
Classifier: Topic :: Software Development :: Libraries :: Python Modules
